[
  {
    "ContainingType": "dizajni_i_sistemit_softuerik.Controllers.ClientsController",
    "Method": "Get",
    "RelativePath": "api/Clients",
    "HttpMethod": "GET",
    "IsController": true,
    "Order": 0,
    "Parameters": [],
    "ReturnTypes": [
      {
        "Type": "System.Collections.Generic.IEnumerable\u00601[[dizajni_i_sistemit_softuerik.Entities.Client, dizajni_i_sistemit_softuerik, Version=1.0.0.0, Culture=neutral, PublicKeyToken=null]]",
        "MediaTypes": [
          "text/plain",
          "application/json",
          "text/json"
        ],
        "StatusCode": 200
      }
    ]
  },
  {
    "ContainingType": "dizajni_i_sistemit_softuerik.Controllers.ClientsController",
    "Method": "Create",
    "RelativePath": "api/Clients",
    "HttpMethod": "POST",
    "IsController": true,
    "Order": 0,
    "Parameters": [
      {
        "Name": "client",
        "Type": "dizajni_i_sistemit_softuerik.Entities.Client",
        "IsRequired": true
      }
    ],
    "ReturnTypes": []
  },
  {
    "ContainingType": "dizajni_i_sistemit_softuerik.Controllers.ClientsController",
    "Method": "Get",
    "RelativePath": "api/Clients/{id}",
    "HttpMethod": "GET",
    "IsController": true,
    "Order": 0,
    "Parameters": [
      {
        "Name": "id",
        "Type": "System.Int32",
        "IsRequired": true
      }
    ],
    "ReturnTypes": [
      {
        "Type": "dizajni_i_sistemit_softuerik.Entities.Client",
        "MediaTypes": [
          "text/plain",
          "application/json",
          "text/json"
        ],
        "StatusCode": 200
      }
    ]
  },
  {
    "ContainingType": "dizajni_i_sistemit_softuerik.Controllers.ClientsController",
    "Method": "Update",
    "RelativePath": "api/Clients/{id}",
    "HttpMethod": "PUT",
    "IsController": true,
    "Order": 0,
    "Parameters": [
      {
        "Name": "id",
        "Type": "System.Int32",
        "IsRequired": true
      },
      {
        "Name": "client",
        "Type": "dizajni_i_sistemit_softuerik.Entities.Client",
        "IsRequired": true
      }
    ],
    "ReturnTypes": []
  },
  {
    "ContainingType": "dizajni_i_sistemit_softuerik.Controllers.ClientsController",
    "Method": "Delete",
    "RelativePath": "api/Clients/{id}",
    "HttpMethod": "DELETE",
    "IsController": true,
    "Order": 0,
    "Parameters": [
      {
        "Name": "id",
        "Type": "System.Int32",
        "IsRequired": true
      }
    ],
    "ReturnTypes": []
  },
  {
    "ContainingType": "dizajni_i_sistemit_softuerik.Controllers.IngredientsController",
    "Method": "Get",
    "RelativePath": "api/Ingredients",
    "HttpMethod": "GET",
    "IsController": true,
    "Order": 0,
    "Parameters": [],
    "ReturnTypes": [
      {
        "Type": "System.Collections.Generic.IEnumerable\u00601[[dizajni_i_sistemit_softuerik.Entities.Ingredient, dizajni_i_sistemit_softuerik, Version=1.0.0.0, Culture=neutral, PublicKeyToken=null]]",
        "MediaTypes": [
          "text/plain",
          "application/json",
          "text/json"
        ],
        "StatusCode": 200
      }
    ]
  },
  {
    "ContainingType": "dizajni_i_sistemit_softuerik.Controllers.IngredientsController",
    "Method": "Create",
    "RelativePath": "api/Ingredients",
    "HttpMethod": "POST",
    "IsController": true,
    "Order": 0,
    "Parameters": [
      {
        "Name": "ingredient",
        "Type": "dizajni_i_sistemit_softuerik.Entities.Ingredient",
        "IsRequired": true
      }
    ],
    "ReturnTypes": []
  },
  {
    "ContainingType": "dizajni_i_sistemit_softuerik.Controllers.IngredientsController",
    "Method": "Get",
    "RelativePath": "api/Ingredients/{id}",
    "HttpMethod": "GET",
    "IsController": true,
    "Order": 0,
    "Parameters": [
      {
        "Name": "id",
        "Type": "System.Int32",
        "IsRequired": true
      }
    ],
    "ReturnTypes": [
      {
        "Type": "dizajni_i_sistemit_softuerik.Entities.Ingredient",
        "MediaTypes": [
          "text/plain",
          "application/json",
          "text/json"
        ],
        "StatusCode": 200
      }
    ]
  },
  {
    "ContainingType": "dizajni_i_sistemit_softuerik.Controllers.IngredientsController",
    "Method": "Update",
    "RelativePath": "api/Ingredients/{id}",
    "HttpMethod": "PUT",
    "IsController": true,
    "Order": 0,
    "Parameters": [
      {
        "Name": "id",
        "Type": "System.Int32",
        "IsRequired": true
      },
      {
        "Name": "ingredient",
        "Type": "dizajni_i_sistemit_softuerik.Entities.Ingredient",
        "IsRequired": true
      }
    ],
    "ReturnTypes": []
  },
  {
    "ContainingType": "dizajni_i_sistemit_softuerik.Controllers.IngredientsController",
    "Method": "Delete",
    "RelativePath": "api/Ingredients/{id}",
    "HttpMethod": "DELETE",
    "IsController": true,
    "Order": 0,
    "Parameters": [
      {
        "Name": "id",
        "Type": "System.Int32",
        "IsRequired": true
      }
    ],
    "ReturnTypes": []
  },
  {
    "ContainingType": "dizajni_i_sistemit_softuerik.Controllers.OrderItemsController",
    "Method": "Get",
    "RelativePath": "api/OrderItems",
    "HttpMethod": "GET",
    "IsController": true,
    "Order": 0,
    "Parameters": [],
    "ReturnTypes": [
      {
        "Type": "System.Collections.Generic.IEnumerable\u00601[[dizajni_i_sistemit_softuerik.Entities.OrderItem, dizajni_i_sistemit_softuerik, Version=1.0.0.0, Culture=neutral, PublicKeyToken=null]]",
        "MediaTypes": [
          "text/plain",
          "application/json",
          "text/json"
        ],
        "StatusCode": 200
      }
    ]
  },
  {
    "ContainingType": "dizajni_i_sistemit_softuerik.Controllers.OrderItemsController",
    "Method": "Create",
    "RelativePath": "api/OrderItems",
    "HttpMethod": "POST",
    "IsController": true,
    "Order": 0,
    "Parameters": [
      {
        "Name": "orderItem",
        "Type": "dizajni_i_sistemit_softuerik.Entities.OrderItem",
        "IsRequired": true
      }
    ],
    "ReturnTypes": []
  },
  {
    "ContainingType": "dizajni_i_sistemit_softuerik.Controllers.OrderItemsController",
    "Method": "Get",
    "RelativePath": "api/OrderItems/{id}",
    "HttpMethod": "GET",
    "IsController": true,
    "Order": 0,
    "Parameters": [
      {
        "Name": "id",
        "Type": "System.Int32",
        "IsRequired": true
      }
    ],
    "ReturnTypes": [
      {
        "Type": "dizajni_i_sistemit_softuerik.Entities.OrderItem",
        "MediaTypes": [
          "text/plain",
          "application/json",
          "text/json"
        ],
        "StatusCode": 200
      }
    ]
  },
  {
    "ContainingType": "dizajni_i_sistemit_softuerik.Controllers.OrderItemsController",
    "Method": "Update",
    "RelativePath": "api/OrderItems/{id}",
    "HttpMethod": "PUT",
    "IsController": true,
    "Order": 0,
    "Parameters": [
      {
        "Name": "id",
        "Type": "System.Int32",
        "IsRequired": true
      },
      {
        "Name": "orderItem",
        "Type": "dizajni_i_sistemit_softuerik.Entities.OrderItem",
        "IsRequired": true
      }
    ],
    "ReturnTypes": []
  },
  {
    "ContainingType": "dizajni_i_sistemit_softuerik.Controllers.OrderItemsController",
    "Method": "Delete",
    "RelativePath": "api/OrderItems/{id}",
    "HttpMethod": "DELETE",
    "IsController": true,
    "Order": 0,
    "Parameters": [
      {
        "Name": "id",
        "Type": "System.Int32",
        "IsRequired": true
      }
    ],
    "ReturnTypes": []
  },
  {
    "ContainingType": "dizajni_i_sistemit_softuerik.Controllers.OrdersController",
    "Method": "Get",
    "RelativePath": "api/Orders",
    "HttpMethod": "GET",
    "IsController": true,
    "Order": 0,
    "Parameters": [],
    "ReturnTypes": [
      {
        "Type": "System.Collections.Generic.IEnumerable\u00601[[dizajni_i_sistemit_softuerik.Entities.Order, dizajni_i_sistemit_softuerik, Version=1.0.0.0, Culture=neutral, PublicKeyToken=null]]",
        "MediaTypes": [
          "text/plain",
          "application/json",
          "text/json"
        ],
        "StatusCode": 200
      }
    ]
  },
  {
    "ContainingType": "dizajni_i_sistemit_softuerik.Controllers.OrdersController",
    "Method": "Create",
    "RelativePath": "api/Orders",
    "HttpMethod": "POST",
    "IsController": true,
    "Order": 0,
    "Parameters": [
      {
        "Name": "order",
        "Type": "dizajni_i_sistemit_softuerik.Entities.Order",
        "IsRequired": true
      }
    ],
    "ReturnTypes": []
  },
  {
    "ContainingType": "dizajni_i_sistemit_softuerik.Controllers.OrdersController",
    "Method": "Get",
    "RelativePath": "api/Orders/{id}",
    "HttpMethod": "GET",
    "IsController": true,
    "Order": 0,
    "Parameters": [
      {
        "Name": "id",
        "Type": "System.Int32",
        "IsRequired": true
      }
    ],
    "ReturnTypes": [
      {
        "Type": "dizajni_i_sistemit_softuerik.Entities.Order",
        "MediaTypes": [
          "text/plain",
          "application/json",
          "text/json"
        ],
        "StatusCode": 200
      }
    ]
  },
  {
    "ContainingType": "dizajni_i_sistemit_softuerik.Controllers.OrdersController",
    "Method": "Update",
    "RelativePath": "api/Orders/{id}",
    "HttpMethod": "PUT",
    "IsController": true,
    "Order": 0,
    "Parameters": [
      {
        "Name": "id",
        "Type": "System.Int32",
        "IsRequired": true
      },
      {
        "Name": "order",
        "Type": "dizajni_i_sistemit_softuerik.Entities.Order",
        "IsRequired": true
      }
    ],
    "ReturnTypes": []
  },
  {
    "ContainingType": "dizajni_i_sistemit_softuerik.Controllers.OrdersController",
    "Method": "Delete",
    "RelativePath": "api/Orders/{id}",
    "HttpMethod": "DELETE",
    "IsController": true,
    "Order": 0,
    "Parameters": [
      {
        "Name": "id",
        "Type": "System.Int32",
        "IsRequired": true
      }
    ],
    "ReturnTypes": []
  },
  {
    "ContainingType": "dizajni_i_sistemit_softuerik.Controllers.ProductsController",
    "Method": "Get",
    "RelativePath": "api/Products",
    "HttpMethod": "GET",
    "IsController": true,
    "Order": 0,
    "Parameters": [],
    "ReturnTypes": [
      {
        "Type": "System.Collections.Generic.IEnumerable\u00601[[dizajni_i_sistemit_softuerik.Entities.Product, dizajni_i_sistemit_softuerik, Version=1.0.0.0, Culture=neutral, PublicKeyToken=null]]",
        "MediaTypes": [
          "text/plain",
          "application/json",
          "text/json"
        ],
        "StatusCode": 200
      }
    ]
  },
  {
    "ContainingType": "dizajni_i_sistemit_softuerik.Controllers.ProductsController",
    "Method": "Create",
    "RelativePath": "api/Products",
    "HttpMethod": "POST",
    "IsController": true,
    "Order": 0,
    "Parameters": [
      {
        "Name": "product",
        "Type": "dizajni_i_sistemit_softuerik.Entities.Product",
        "IsRequired": true
      }
    ],
    "ReturnTypes": []
  },
  {
    "ContainingType": "dizajni_i_sistemit_softuerik.Controllers.ProductsController",
    "Method": "Get",
    "RelativePath": "api/Products/{id}",
    "HttpMethod": "GET",
    "IsController": true,
    "Order": 0,
    "Parameters": [
      {
        "Name": "id",
        "Type": "System.Int32",
        "IsRequired": true
      }
    ],
    "ReturnTypes": [
      {
        "Type": "dizajni_i_sistemit_softuerik.Entities.Product",
        "MediaTypes": [
          "text/plain",
          "application/json",
          "text/json"
        ],
        "StatusCode": 200
      }
    ]
  },
  {
    "ContainingType": "dizajni_i_sistemit_softuerik.Controllers.ProductsController",
    "Method": "Update",
    "RelativePath": "api/Products/{id}",
    "HttpMethod": "PUT",
    "IsController": true,
    "Order": 0,
    "Parameters": [
      {
        "Name": "id",
        "Type": "System.Int32",
        "IsRequired": true
      },
      {
        "Name": "product",
        "Type": "dizajni_i_sistemit_softuerik.Entities.Product",
        "IsRequired": true
      }
    ],
    "ReturnTypes": []
  },
  {
    "ContainingType": "dizajni_i_sistemit_softuerik.Controllers.ProductsController",
    "Method": "Delete",
    "RelativePath": "api/Products/{id}",
    "HttpMethod": "DELETE",
    "IsController": true,
    "Order": 0,
    "Parameters": [
      {
        "Name": "id",
        "Type": "System.Int32",
        "IsRequired": true
      }
    ],
    "ReturnTypes": []
  },
  {
    "ContainingType": "dizajni_i_sistemit_softuerik.Controllers.ReservationsController",
    "Method": "Get",
    "RelativePath": "api/Reservations",
    "HttpMethod": "GET",
    "IsController": true,
    "Order": 0,
    "Parameters": [],
    "ReturnTypes": [
      {
        "Type": "System.Collections.Generic.IEnumerable\u00601[[dizajni_i_sistemit_softuerik.Entities.Reservation, dizajni_i_sistemit_softuerik, Version=1.0.0.0, Culture=neutral, PublicKeyToken=null]]",
        "MediaTypes": [
          "text/plain",
          "application/json",
          "text/json"
        ],
        "StatusCode": 200
      }
    ]
  },
  {
    "ContainingType": "dizajni_i_sistemit_softuerik.Controllers.ReservationsController",
    "Method": "Create",
    "RelativePath": "api/Reservations",
    "HttpMethod": "POST",
    "IsController": true,
    "Order": 0,
    "Parameters": [
      {
        "Name": "reservation",
        "Type": "dizajni_i_sistemit_softuerik.Entities.Reservation",
        "IsRequired": true
      }
    ],
    "ReturnTypes": []
  },
  {
    "ContainingType": "dizajni_i_sistemit_softuerik.Controllers.ReservationsController",
    "Method": "Get",
    "RelativePath": "api/Reservations/{id}",
    "HttpMethod": "GET",
    "IsController": true,
    "Order": 0,
    "Parameters": [
      {
        "Name": "id",
        "Type": "System.Int32",
        "IsRequired": true
      }
    ],
    "ReturnTypes": [
      {
        "Type": "dizajni_i_sistemit_softuerik.Entities.Reservation",
        "MediaTypes": [
          "text/plain",
          "application/json",
          "text/json"
        ],
        "StatusCode": 200
      }
    ]
  },
  {
    "ContainingType": "dizajni_i_sistemit_softuerik.Controllers.ReservationsController",
    "Method": "Update",
    "RelativePath": "api/Reservations/{id}",
    "HttpMethod": "PUT",
    "IsController": true,
    "Order": 0,
    "Parameters": [
      {
        "Name": "id",
        "Type": "System.Int32",
        "IsRequired": true
      },
      {
        "Name": "reservation",
        "Type": "dizajni_i_sistemit_softuerik.Entities.Reservation",
        "IsRequired": true
      }
    ],
    "ReturnTypes": []
  },
  {
    "ContainingType": "dizajni_i_sistemit_softuerik.Controllers.ReservationsController",
    "Method": "Delete",
    "RelativePath": "api/Reservations/{id}",
    "HttpMethod": "DELETE",
    "IsController": true,
    "Order": 0,
    "Parameters": [
      {
        "Name": "id",
        "Type": "System.Int32",
        "IsRequired": true
      }
    ],
    "ReturnTypes": []
  },
  {
    "ContainingType": "dizajni_i_sistemit_softuerik.Controllers.WeatherForecastController",
    "Method": "Get",
    "RelativePath": "WeatherForecast",
    "HttpMethod": "GET",
    "IsController": true,
    "Order": 0,
    "Parameters": [],
    "ReturnTypes": [
      {
        "Type": "System.Collections.Generic.IEnumerable\u00601[[dizajni_i_sistemit_softuerik.WeatherForecast, dizajni_i_sistemit_softuerik, Version=1.0.0.0, Culture=neutral, PublicKeyToken=null]]",
        "MediaTypes": [
          "text/plain",
          "application/json",
          "text/json"
        ],
        "StatusCode": 200
      }
    ],
    "EndpointName": "GetWeatherForecast"
  }
]